kgraphgnn/__init__.py
kgraphgnn-0.0.1.dist-info/LICENSE
kgraphgnn-0.0.1.dist-info/METADATA
kgraphgnn-0.0.1.dist-info/WHEEL
kgraphgnn-0.0.1.dist-info/top_level.txt
kgraphgnn-0.0.1.dist-info/RECORD
