Metadata-Version: 2.1
Name: kgraphgnn
Version: 0.0.1
Summary: KGraph GNN
Home-page: https://github.com/vital-ai/kgraph-gnn
Author: Marc Hadfield
Author-email: marc@vital.ai
License: Apache License 2.0
Classifier: Programming Language :: Python :: 3.11
Classifier: License :: OSI Approved :: Apache Software License
Classifier: Operating System :: OS Independent
Requires-Python: >=3.11
License-File: LICENSE
Requires-Dist: vital-ai-vitalsigns>=0.1.27
Requires-Dist: vital-ai-domain>=0.1.4
Requires-Dist: pyyaml
Requires-Dist: vital-ai-haley-kg>=0.1.24
Requires-Dist: kgraphservice>=0.0.6
Requires-Dist: torch-geometric==2.6.1
